{"stats":{"minecraft:used":{"minecraft:barrier":4,"minecraft:smooth_sandstone":27,"minecraft:debug_stick":8,"minecraft:fire_coral_block":8,"minecraft:bricks":143,"minecraft:terracotta":12,"minecraft:orange_terracotta":5,"minecraft:dead_fire_coral_block":1},"minecraft:dropped":{"minecraft:debug_stick":11,"minecraft:fire_coral_block":1},"minecraft:custom":{"minecraft:jump":145,"minecraft:time_since_rest":37233,"minecraft:crouch_one_cm":1167,"minecraft:play_one_minute":37233,"minecraft:leave_game":1,"minecraft:sprint_one_cm":25059,"minecraft:time_since_death":37233,"minecraft:walk_one_cm":39156,"minecraft:sneak_time":2081,"minecraft:climb_one_cm":202,"minecraft:drop":12,"minecraft:fly_one_cm":428854}},"DataVersion":2567}