{"stats":{"minecraft:dropped":{"minecraft:golden_horse_armor":1,"minecraft:spider_eye":2,"minecraft:slime_block":1,"minecraft:bone":1},"minecraft:killed":{"minecraft:evoker":5,"minecraft:cave_spider":9,"minecraft:slime":5,"minecraft:villager":24},"minecraft:used":{"minecraft:birch_fence":1,"minecraft:sea_lantern":5,"minecraft:trident":83,"minecraft:wooden_hoe":8,"minecraft:jungle_leaves":1,"minecraft:black_wool":11,"minecraft:iron_bars":7,"minecraft:stone_sword":24,"minecraft:crying_obsidian":56,"minecraft:command_block":2,"minecraft:warped_hyphae":36,"minecraft:acacia_slab":2,"minecraft:light_weighted_pressure_plate":2,"minecraft:red_concrete":3,"minecraft:brown_stained_glass":52,"minecraft:carrot_on_a_stick":3222,"minecraft:slime_block":1,"minecraft:barrier":22,"minecraft:oak_planks":2,"minecraft:red_nether_bricks":3,"minecraft:green_wool":4,"minecraft:stone_slab":2,"minecraft:spruce_trapdoor":1,"minecraft:composter":1,"minecraft:redstone_block":2,"minecraft:stripped_jungle_wood":2,"minecraft:clay":5,"minecraft:diamond_axe":4,"minecraft:prismarine_slab":1,"minecraft:polished_andesite_slab":6,"minecraft:stone_bricks":13,"minecraft:golden_apple":18,"minecraft:debug_stick":12,"minecraft:bedrock":46,"minecraft:oak_leaves":2,"minecraft:potion":59,"minecraft:torch":6,"minecraft:glowstone":12,"minecraft:nether_wart_block":5,"minecraft:anvil":1,"minecraft:redstone_lamp":1,"minecraft:cobblestone":2,"minecraft:bow":323,"minecraft:crimson_hyphae":9,"minecraft:orange_wool":19,"minecraft:gold_block":3,"minecraft:birch_sign":1,"minecraft:light_gray_concrete_powder":20,"minecraft:sponge":11,"minecraft:green_concrete_powder":3,"minecraft:cobblestone_wall":1,"minecraft:repeating_command_block":5,"minecraft:jungle_slab":7,"minecraft:stone_stairs":14,"minecraft:oak_wood":3,"minecraft:cyan_concrete_powder":6,"minecraft:cyan_wool":22,"minecraft:cyan_stained_glass":1},"minecraft:custom":{"minecraft:time_since_rest":1450373,"minecraft:damage_taken":8488,"minecraft:sprint_one_cm":3208320,"minecraft:walk_one_cm":1292422,"minecraft:mob_kills":53,"minecraft:drop":5,"minecraft:damage_dealt":5244,"minecraft:swim_one_cm":2510,"minecraft:talked_to_villager":3,"minecraft:fly_one_cm":5339738,"minecraft:crouch_one_cm":37994,"minecraft:play_time":1780577,"minecraft:deaths":1,"minecraft:sneak_time":14837,"minecraft:walk_under_water_one_cm":6404,"minecraft:jump":11512,"minecraft:damage_dealt_resisted":151,"minecraft:leave_game":48,"minecraft:time_since_death":1450372,"minecraft:walk_on_water_one_cm":15450,"minecraft:total_world_time":17823,"minecraft:climb_one_cm":3634,"minecraft:damage_resisted":23742,"minecraft:fall_one_cm":1055773},"minecraft:broken":{"minecraft:trident":5}},"DataVersion":2730}